OpenDiscord/__init__.py
OpenDiscord/arcane_center.py
OpenDiscord/blist.py
OpenDiscord/botsondiscord.py
OpenDiscord/discordlabs.py
OpenDiscord-0.0.3.dist-info/LICENSE
OpenDiscord-0.0.3.dist-info/METADATA
OpenDiscord-0.0.3.dist-info/WHEEL
OpenDiscord-0.0.3.dist-info/top_level.txt
OpenDiscord-0.0.3.dist-info/RECORD
