Metadata-Version: 2.1
Name: OpenDiscord
Version: 0.0.3
Summary: An API wrapper for common discord bot listing sites.
Home-page: https://github.com/pjotr07740/OpenDiscord
Author: Pjotr
Author-email: pjotrlspdfr@outlook.com
License: UNKNOWN
Platform: UNKNOWN
Classifier: Programming Language :: Python :: 3
Classifier: License :: OSI Approved :: MIT License
Classifier: Operating System :: OS Independent
Requires-Python: >=3.6
